Workbook
Name Lookup_Table: 'Analysis - 1'!$R$4:$X$8
Name Slicer_Country: #N/A
Name Slicer_Month_Name: #N/A
Name Slicer_Year: #N/A

Sheet Analysis - 1
A4: #Transaction | B4: COGS | C4: Total Revenue | D4: Total Profit | E4: OrderQuantity | F4: All Products | G4: Sold Products | H4: Unsold Products | I4: % Profit Margin | M4: Year | N4: Revenue | O4: Total Profit | P4: #Transaction | R4: Row Labels | S4: #Transaction | T4: COGS | U4: Total Revenue | V4: Total Profit | W4: OrderQuantity | X4: % Profit Margin
A5: 60398 | B5: 1.8080237e+08 | C5: 3.0709295e+08 | D5: 1.2629058e+08 | E5: 60398 | F5: 606 | G5: 158 | H5: 448 | I5: 0.41124545 | M5: 2005 | N5: 33370192 | O5: 13403627 | P5: 1013 | R5: 2005 | S5: 1013 | T5: 19966566 | U5: 33370192 | V5: 13403627 | W5: 1013 | X5: 0.40166465
M6: 2006 | N6: 69484523 | O6: 28177776 | P6: 2677 | R6: 2006 | S6: 2677 | T6: 41306747 | U6: 69484523 | V6: 28177776 | W6: 2677 | X6: 0.40552594
M7: 2007 | N7: 1.0237961e+08 | O7: 42547111 | P7: 24443 | R7: 2007 | S7: 24443 | T7: 59832502 | U7: 1.0237961e+08 | V7: 42547111 | W7: 24443 | X7: 0.41558187
M8: 2008 | N8: 1.0185862e+08 | O8: 42162064 | P8: 32265 | R8: 2008 | S8: 32265 | T8: 59696553 | U8: 1.0185862e+08 | V8: 42162064 | W8: 32265 | X8: 0.41392732
B9: Year | C9: Revenue | D9: Total Profit | E9: #Transaction
B10: 2005 | C10: 33370192 | D10: 13403627 | E10: 1013 | P10: Year
B11: 2006 | C11: 69484523 | D11: 28177776 | E11: 2677 | M11: Check Selected Year | N11: 1 | P11: 2005
B12: 2007 | C12: 1.0237961e+08 | D12: 42547111 | E12: 24443 | P12: 2006
B13: 2008 | C13: 1.0185862e+08 | D13: 42162064 | E13: 32265 | P13: 2007
P14: 2008
C15: option button | D15: 2 | M15: Total Profit | N15: Year | O15: Profit | R15: Total COGS | S15: Year | T15: COGS | U15: Percentage | W15: % Profit Margin | X15: Year | Y15: Profit Margin | Z15: Percentage
M16: Selected Year | N16: =IF(N11=1,P11,0) -> 2005 | O16: =IFERROR(VLOOKUP('Analysis - 1'!N16,Lookup_Table,5,0),0) -> 13403627 | P16: =IFERROR($O16/SUM($O$16:$O$17),0) -> 1 | R16: Selected Year | S16: =IF(N11=1,P11,0) -> 2005 | T16: =IFERROR(VLOOKUP('Analysis - 1'!S16,Lookup_Table,3,0),0) -> 19966566 | U16: =IFERROR($T16/SUM($T$16:$T$17),0) -> 1 | W16: Selected Year | X16: =IF(N11=1,P11,0) -> 2005 | Y16: =IFERROR(VLOOKUP('Analysis - 1'!X16,Lookup_Table,7,0),0) -> 0.40166465 | Z16: =IFERROR($Y16/SUM($Y$16:$Y$17),0) -> 1
B17: Year | C17: {=_xlfn.IFS($D$15=1,C9,$D$15=2,D9,$D$15=3,E9)} -> Total Profit | D17: ="Average"&" "& C17 -> Average Total Profit | E17: Aboce Average | M17: Previous Year | N17: =$P$11-1 -> 2004 | O17: =IFERROR(VLOOKUP('Analysis - 1'!N17,Lookup_Table,5,0),0) -> 0 | P17: =IFERROR($O17/SUM($O$16:$O$17),0) -> 0 | R17: Previous Year | S17: =$P$11-1 -> 2004 | T17: =IFERROR(VLOOKUP('Analysis - 1'!S17,Lookup_Table,3,0),0) -> 0 | U17: =IFERROR($T17/SUM($T$16:$T$17),0) -> 0 | W17: Previous Year | X17: =$P$11-1 -> 2004 | Y17: =IFERROR(VLOOKUP('Analysis - 1'!X17,Lookup_Table,7,0),0) -> 0 | Z17: =IFERROR($Y17/SUM($Y$16:$Y$17),0) -> 0
B18: 2005 | C18: {=_xlfn.IFS($D$15=1,C10,$D$15=2,D10,$D$15=3,E10)} -> 13403627 | D18: =AVERAGE($C$18:$C$21) -> 31572644 | E18: =IF(C18>D18,C18,"")
B19: 2006 | C19: {=_xlfn.IFS($D$15=1,C11,$D$15=2,D11,$D$15=3,E11)} -> 28177776 | D19: =AVERAGE($C$18:$C$21) -> 31572644 | E19: =IF(C19>D19,C19,"") | M19: YoY Change | N19: =P16-P17 -> 1 | R19: YoY Change | S19: =U16-U17 -> 1 | W19: YoY Change | X19: =Z16-Z17 -> 1
B20: 2007 | C20: {=_xlfn.IFS($D$15=1,C12,$D$15=2,D12,$D$15=3,E12)} -> 42547111 | D20: =AVERAGE($C$18:$C$21) -> 31572644 | E20: =IF(C20>D20,C20,"") -> 42547111
B21: 2008 | C21: {=_xlfn.IFS($D$15=1,C13,$D$15=2,D13,$D$15=3,E13)} -> 42162064 | D21: =AVERAGE($C$18:$C$21) -> 31572644 | E21: =IF(C21>D21,C21,"") -> 42162064 | M21: Total Revenue | N21: Year | O21: Revenue | P21: Percentage | R21: Total Quantity | S21: Year | T21: QTY | U21: Percentage | W21: Transaction | X21: Year | Y21: Transaction | Z21: Percentage
M22: Selected Year | N22: =IF(N11=1,P11,0) -> 2005 | O22: =IFERROR(VLOOKUP('Analysis - 1'!N22,Lookup_Table,4,0),0) -> 33370192 | P22: =IFERROR($O22/SUM($O$22:$O$23),0) -> 1 | R22: Selected Year | S22: =IF(N11=1,P11,0) -> 2005 | T22: =IFERROR(VLOOKUP('Analysis - 1'!S22,Lookup_Table,6,0),0) -> 1013 | U22: =IFERROR($T22/SUM($T$22:$T$23),0) -> 1 | W22: Selected Year | X22: =IF(N11=1,P11,0) -> 2005 | Y22: =IFERROR(VLOOKUP('Analysis - 1'!X22,Lookup_Table,2,0),0) -> 1013 | Z22: =IFERROR($Y22/SUM($Y$22:$Y$23),0) -> 1
M23: Previous Year | N23: =$P$11-1 -> 2004 | O23: =IFERROR(VLOOKUP('Analysis - 1'!N23,Lookup_Table,4,0),0) -> 0 | P23: =IFERROR($O23/SUM($O$22:$O$23),0) -> 0 | R23: Previous Year | S23: =$P$11-1 -> 2004 | T23: =IFERROR(VLOOKUP('Analysis - 1'!S23,Lookup_Table,6,0),0) -> 0 | U23: =IFERROR($T23/SUM($T$22:$T$23),0) -> 0 | W23: Previous Year | X23: =$P$11-1 -> 2004 | Y23: =IFERROR(VLOOKUP('Analysis - 1'!X23,Lookup_Table,2,0),0) -> 0 | Z23: =IFERROR($Y23/SUM($Y$22:$Y$23),0) -> 0
B24: Above Average | D24: Caption
A25: Total | B25: =SUM(E18:E21) -> 84709175 | D25: ="of" &" "& C17 &" "&"comes from the highlighted years" -> of Total Profit comes from the highlighted years | M25: YoY Change | N25: =P22-P23 -> 1 | R25: YoY Change | S25: =U22-U23 -> 1 | W25: YoY Change | X25: =Z22-Z23 -> 1
A26: Percentage | B26: =B25/SUM(C18:C21) -> 0.67074818

Sheet Analysis - 2
B4: Month Name | C4: Total Profit
B5: Jan | C5: 10223846 | J5: 1 | K5: =LARGE($C$5:$C$16,J5) -> 13733395 | L5: =INDEX($B$5:$B$16,MATCH($K5,C5:C16,0)) -> May
B6: Feb | C6: 10792830 | J6: 2 | K6: =LARGE($C$5:$C$16,J6) -> 13445658 | L6: =INDEX($B$5:$B$16,MATCH($K6,C6:C17,0)) -> May
B7: Mar | C7: 11283963 | J7: 3 | K7: =LARGE($C$5:$C$16,J7) -> 13143417 | L7: =INDEX($B$5:$B$16,MATCH($K7,C7:C18,0)) -> Oct
B8: Apr | C8: 11839838
B9: May | C9: 13733395 | K9: =SUM(K5:K7)/SUM(C5:C16) -> 0.31928329
B10: Jun | C10: 13445658
B11: Jul | C11: 8108100.7 | K11: ="In"&" "&'Analysis - 1'!P11 -> In 2005
B12: Aug | C12: 8035078.6
B13: Sep | C13: 8046581.2
B14: Oct | C14: 8675444.4
B15: Nov | C15: 8962424.9
B16: Dec | C16: 13143417
B21: Day Name | C21: Total Profit | E21: =B21 -> Day Name | F21: =C21 -> Total Profit | G21: Highlights
B22: Mon | C22: 17943295 | E22: =B22 -> Mon | F22: =C22 -> 17943295 | G22: {=IFERROR(_xlfn.IFS(F22=$C$31,F22,F22=$C$32,F22,F22=$C$33,F22)," ")}
B23: Tue | C23: 17685313 | E23: =B23 -> Tue | F23: =C23 -> 17685313 | G23: {=IFERROR(_xlfn.IFS(F23=$C$31,F23,F23=$C$32,F23,F23=$C$33,F23)," ")}
B24: Wed | C24: 18218770 | E24: =B24 -> Wed | F24: =C24 -> 18218770 | G24: {=IFERROR(_xlfn.IFS(F24=$C$31,F24,F24=$C$32,F24,F24=$C$33,F24)," ")} -> 18218770
B25: Thu | C25: 18810562 | E25: =B25 -> Thu | F25: =C25 -> 18810562 | G25: {=IFERROR(_xlfn.IFS(F25=$C$31,F25,F25=$C$32,F25,F25=$C$33,F25)," ")} -> 18810562
B26: Fri | C26: 18279688 | E26: =B26 -> Fri | F26: =C26 -> 18279688 | G26: {=IFERROR(_xlfn.IFS(F26=$C$31,F26,F26=$C$32,F26,F26=$C$33,F26)," ")} -> 18279688
B27: Sat | C27: 17729640 | E27: =B27 -> Sat | F27: =C27 -> 17729640 | G27: {=IFERROR(_xlfn.IFS(F27=$C$31,F27,F27=$C$32,F27,F27=$C$33,F27)," ")}
B28: Sun | C28: 17623310 | E28: =B28 -> Sun | F28: =C28 -> 17623310 | G28: {=IFERROR(_xlfn.IFS(F28=$C$31,F28,F28=$C$32,F28,F28=$C$33,F28)," ")}
B31: 1 | C31: =LARGE($F$22:$F$28,B31) -> 18810562 | F31: =SUM(G22:G28)/SUM(F22:F28) -> 0.43795048
B32: 2 | C32: =LARGE($F$22:$F$28,B32) -> 18279688
B33: 3 | C33: =LARGE($F$22:$F$28,B33) -> 18218770
B41: Week Types | C41: Total Profit | D41: %
B42: Weekday | C42: 90937627 | D42: =C42/SUM(C42:C43) -> 0.7200666
B43: Weekend | C43: 35352950 | D43: =C43/SUM($C$42:$C$43) -> 0.2799334
B45: Top
B46: =MAX(D42:D43) -> 0.7200666
B47: =INDEX(B42:B43,MATCH(B46,D42:D43,0))&" "&"Make up" -> Weekday Make up
B59: Quarter | C59: Total Profit | D59: Sum of Total Profit
B60: Q1 | C60: 32300639 | D60: 0.25576444
B61: Q2 | C61: 39018891 | D61: 0.30896122
B62: Q3 | C62: 24189761 | D62: 0.1915405
B63: Q4 | C63: 30781287 | D63: 0.24373383

Sheet Products & Customers Analysis
H2: Products | I2: Profit | J2: Percentage
B3: Month Name | C3: Total Profit | E3: =B3 -> Month Name | F3: =C3 -> Total Profit | H3: Top - 5 | I3: =SUM(F4:F8) -> 31270388 | J3: =I3/SUM($I$3:$I$4) -> 0.55906791
B4: Mountain-200 Black, 46 | C4: 6607699.9 | E4: =B4 -> Mountain-200 Black, 46 | F4: =C4 -> 6607699.9 | H4: Others | I4: =SUM(F5:F9) -> 24662688 | J4: =I4/SUM($I$3:$I$4) -> 0.44093209 | R4: All Products | S4: Sold Products | T4: Unsold Products | Z4: #Customers | AA4: Average Customer Age
B5: Mountain-200 Black, 42 | C5: 6413590.1 | E5: =B5 -> Mountain-200 Black, 42 | F5: =C5 -> 6413590.1 | R5: 606 | S5: 158 | T5: 448 | Z5: 18484 | AA5: 45.595975
B6: Mountain-200 Silver, 46 | C6: 6142629.2 | E6: =B6 -> Mountain-200 Silver, 46 | F6: =C6 -> 6142629.2
B7: Mountain-200 Black, 38 | C7: 6071041.4 | E7: =B7 -> Mountain-200 Black, 38 | F7: =C7 -> 6071041.4
B8: Mountain-200 Silver, 42 | C8: 6035426.9 | E8: =B8 -> Mountain-200 Silver, 42 | F8: =C8 -> 6035426.9 | R8: Color | S8: Sum of Total Profit | U8: =R8 -> Color | V8: =S8 -> Sum of Total Profit | W8: Highlight | Z8: Gender | AA8: Sum of Total Profit
B9: Mountain-200 Silver, 38 | C9: 6033397.2 | R9: Black | S9: 39160817 | U9: =R9 -> Black | V9: =S9 -> 39160817 | W9: =V9 -> 39160817 | Z9: F | AA9: 63636815
B10: Road-150 Red, 62 | C10: 5022903.6 | E10: Others | R10: Red | S10: 31594382 | U10: =R10 -> Red | V10: =S10 -> 31594382 | W10: =V10 -> 31594382 | Z10: M | AA10: 62653763
B11: Road-150 Red, 48 | C11: 4638799.2 | E11: =B9 -> Mountain-200 Silver, 38 | F11: =C9 -> 6033397.2 | R11: Silver | S11: 23916414 | U11: =R11 -> Silver | V11: =S11 -> 23916414 | W11: =V11 -> 23916414
B12: Road-150 Red, 52 | C12: 4558601.6 | E12: =B10 -> Road-150 Red, 62 | F12: =C10 -> 5022903.6 | R12: Yellow | S12: 19035074 | U12: =R12 -> Yellow | V12: =S12 -> 19035074
B13: Road-150 Red, 56 | C13: 4399613.3 | E13: =B11 -> Road-150 Red, 48 | F13: =C11 -> 4638799.2 | R13: Blue | S13: 9425341 | U13: =R13 -> Blue | V13: =S13 -> 9425341 | Z13: =Z8 -> Gender | AA13: =AA8 -> Sum of Total Profit | AB13: percentage
B14: Road-150 Red, 44 | C14: 4154799.5 | E14: =B12 -> Road-150 Red, 52 | F14: =C12 -> 4558601.6 | R14: Unspecified | S14: 2864789.6 | U14: =R14 -> Unspecified | V14: =S14 -> 2864789.6 | Z14: =Z9 -> F | AA14: =AA9/SUM(AA9:AA10) -> 0.50389202 | AB14: 1
B15: Road-250 Black, 52 | C15: 2931267.1 | E15: =B13 -> Road-150 Red, 56 | F15: =C13 -> 4399613.3 | R15: Multi | S15: 260179.77 | U15: =R15 -> Multi | V15: =S15 -> 260179.77 | Z15: =Z10 -> M | AA15: =AA10/SUM(AA9:AA10) -> 0.49610798 | AB15: 1
B16: Road-250 Red, 58 | C16: 2837717.3 | E16: =B14 -> Road-150 Red, 44 | F16: =C14 -> 4154799.5 | R16: White | S16: 33580.486 | U16: =R16 -> White | V16: =S16 -> 33580.486
B17: Road-250 Black, 48 | C17: 2622907.4 | E17: =B15 -> Road-250 Black, 52 | F17: =C15 -> 2931267.1 | R17: Grey | S17: 0
B18: Road-250 Black, 58 | C18: 2535296.6 | E18: =B16 -> Road-250 Red, 58 | F18: =C16 -> 2837717.3 | R18: Silver/Black | S18: 0
B19: Road-250 Black, 44 | C19: 2442271.2 | E19: =B17 -> Road-250 Black, 48 | F19: =C17 -> 2622907.4
B20: Touring-1000 Blue, 46 | C20: 1752842.7 | E20: =B18 -> Road-250 Black, 58 | F20: =C18 -> 2535296.6
B21: Road-350-W Yellow, 40 | C21: 1621654.6 | E21: =B19 -> Road-250 Black, 44 | F21: =C19 -> 2442271.2
B22: Touring-1000 Yellow, 46 | C22: 1589556.8 | E22: =B20 -> Touring-1000 Blue, 46 | F22: =C20 -> 1752842.7
B23: Road-350-W Yellow, 42 | C23: 1569083.8 | E23: =B21 -> Road-350-W Yellow, 40 | F23: =C21 -> 1621654.6
B24: Road-350-W Yellow, 48 | C24: 1564754.4 | E24: =B22 -> Touring-1000 Yellow, 46 | F24: =C22 -> 1589556.8 | Z24: Age Group | AA24: Total Profit | AD24: =Z24 -> Age Group | AE24: =AA24 -> Total Profit | AF24: Highlights
B25: Touring-1000 Blue, 54 | C25: 1554373.6 | E25: =B23 -> Road-350-W Yellow, 42 | F25: =C23 -> 1569083.8 | Z25: 30 - 34 | AA25: 14868804 | AD25: =Z25 -> 30 - 34 | AE25: =AA25 -> 14868804
B26: Touring-1000 Yellow, 54 | C26: 1551667.2 | E26: =B24 -> Road-350-W Yellow, 48 | F26: =C24 -> 1564754.4 | Z26: 35 - 39 | AA26: 16786359 | AD26: =Z26 -> 35 - 39 | AE26: =AA26 -> 16786359
B27: Road-250 Red, 48 | C27: 1528303.6 | E27: =B25 -> Touring-1000 Blue, 54 | F27: =C25 -> 1554373.6 | Z27: 40 - 44 | AA27: 15801507 | AD27: =Z27 -> 40 - 44 | AE27: =AA27 -> 15801507
B28: Touring-1000 Yellow, 50 | C28: 1489420.1 | E28: =B26 -> Touring-1000 Yellow, 54 | F28: =C26 -> 1551667.2 | Z28: 45 - 49 | AA28: 15143376 | AD28: =Z28 -> 45 - 49 | AE28: =AA28 -> 15143376
B29: Road-350-W Yellow, 44 | C29: 1424977.9 | E29: =B27 -> Road-250 Red, 48 | F29: =C27 -> 1528303.6 | Z29: 50 plus | AA29: 63690532 | AD29: =Z29 -> 50 plus | AE29: =AA29 -> 63690532 | AF29: =AE29 -> 63690532
B30: Touring-1000 Blue, 50 | C30: 1419955.9 | E30: =B28 -> Touring-1000 Yellow, 50 | F30: =C28 -> 1489420.1
B31: Touring-1000 Blue, 60 | C31: 1389283.4 | E31: =B29 -> Road-350-W Yellow, 44 | F31: =C29 -> 1424977.9
B32: Touring-1000 Yellow, 60 | C32: 1381164.2 | E32: =B30 -> Touring-1000 Blue, 50 | F32: =C30 -> 1419955.9
B33: Road-250 Red, 44 | C33: 1357259.4 | E33: =B31 -> Touring-1000 Blue, 60 | F33: =C31 -> 1389283.4
B34: Road-250 Red, 52 | C34: 1270350.4 | E34: =B32 -> Touring-1000 Yellow, 60 | F34: =C32 -> 1381164.2
B35: Road-550-W Yellow, 42 | C35: 1223209.6 | E35: =B33 -> Road-250 Red, 44 | F35: =C33 -> 1357259.4
B36: Road-550-W Yellow, 44 | C36: 1214653.3 | E36: =B34 -> Road-250 Red, 52 | F36: =C34 -> 1270350.4
B37: Road-550-W Yellow, 48 | C37: 1186046.2 | E37: =B35 -> Road-550-W Yellow, 42 | F37: =C35 -> 1223209.6
B38: Road-550-W Yellow, 38 | C38: 1122748.3 | E38: =B36 -> Road-550-W Yellow, 44 | F38: =C36 -> 1214653.3
B39: Road-550-W Yellow, 40 | C39: 1089403.7 | E39: =B37 -> Road-550-W Yellow, 48 | F39: =C37 -> 1186046.2 | H39: Product price type | I39: Sum of Total Profit | R39: Full Name | S39: Sum of Total Profit | U39: =R39 -> Full Name | V39: =S39 -> Sum of Total Profit | W39: Duplicate
B40: Mountain-100 Black, 44 | C40: 977704.89 | E40: =B38 -> Road-550-W Yellow, 38 | F40: =C38 -> 1122748.3 | H40: Expensive | I40: 1.2052131e+08 | R40: Willie Xu | S40: 80609.041 | U40: =R40 -> Willie Xu | V40: =S40 -> 80609.041 | W40: 434.7409
B41: Mountain-100 Black, 48 | C41: 976227.99 | E41: =B39 -> Road-550-W Yellow, 40 | F41: =C39 -> 1089403.7 | H41: Less Expensive | I41: 5769264.5 | R41: Jordan Turner | S41: 78346.273 | U41: =R41 -> Jordan Turner | V41: =S41 -> 78346.273 | W41: 306.6959
B42: Mountain-100 Silver, 38 | C42: 901628.37 | E42: =B40 -> Mountain-100 Black, 44 | F42: =C40 -> 977704.89 | R42: Margaret He | S42: 66024.873 | U42: =R42 -> Margaret He | V42: =S42 -> 66024.873 | W42: 20829.698
B43: Mountain-100 Black, 38 | C43: 837399.81 | E43: =B41 -> Mountain-100 Black, 48 | F43: =C41 -> 976227.99 | H43: =H39 -> Product price type | I43: =I39 -> Sum of Total Profit | J43: Percentage | K43: Max Value | L43: Circle Position | R43: Nichole Nara | S43: 64046.154 | U43: =R43 -> Nichole Nara | V43: =S43 -> 64046.154 | W43: 652.9731
B44: Road-750 Black, 52 | C44: 783201.86 | E44: =B42 -> Mountain-100 Silver, 38 | F44: =C42 -> 901628.37 | H44: =H40 -> Expensive | I44: =I40 -> 1.2052131e+08 | J44: =I44/SUM(I$44:$I$45) -> 0.95431754 | K44: 1 | L44: 0.7 | R44: Dawn Nath | S44: 61984.927 | U44: =R44 -> Dawn Nath | V44: =S44 -> 61984.927 | W44: 604.9077
B45: Mountain-100 Silver, 44 | C45: 778138.02 | E45: =B43 -> Mountain-100 Black, 38 | F45: =C43 -> 837399.81 | H45: =H41 -> Less Expensive | I45: =I41 -> 5769264.5 | J45: =I45/SUM(I$44:$I$45) -> 0.045682462 | K45: 1 | L45: 0.7 | R45: Ricky Vazquez | S45: 61660.064
B46: Road-750 Black, 44 | C46: 772010.45 | E46: =B44 -> Road-750 Black, 52 | F46: =C44 -> 783201.86 | R46: Emily Miller | S46: 61573.701
B47: Road-750 Black, 48 | C47: 726263.14 | E47: =B45 -> Mountain-100 Silver, 44 | F47: =C45 -> 778138.02 | R47: Kate Anand | S47: 61511.864 | U47: Others
B48: Road-750 Black, 58 | C48: 677767.06 | E48: =B46 -> Road-750 Black, 44 | F48: =C46 -> 772010.45 | R48: Ann Martinez | S48: 61461.113
B49: Mountain-100 Silver, 42 | C49: 624890.95 | E49: =B47 -> Road-750 Black, 48 | F49: =C47 -> 726263.14 | R49: Brandi Gill | S49: 60861.289 | U49: Customers | V49: Profits | W49: Percentage | AA49: Max Value | AB49: =MAX(AE25:AE29) -> 63690532
B50: Mountain-100 Black, 42 | C50: 617342.36 | E50: =B48 -> Road-750 Black, 58 | F50: =C48 -> 677767.06 | R50: Aaron Wright | S50: 60682.781 | U50: Top - 5 | V50: =SUM(V40:V44) -> 351011.27 | W50: =V50/SUM($V$50:$V$51) -> 0.002779394
B51: Mountain-400-W Silver, 38 | C51: 564434.52 | E51: =B49 -> Mountain-100 Silver, 42 | F51: =C49 -> 624890.95 | R51: Marc Torres | S51: 59847.957 | U51: Others | V51: =SUM(S45:S18439) -> 1.2593957e+08 | W51: =V51/SUM($V$50:$V$51) -> 0.99722061 | AA51: Percentage Contribution | AB51: =AB49/SUM(AE25:AE29) -> 0.50431737
B52: Mountain-100 Silver, 48 | C52: 523718.13 | E52: =B50 -> Mountain-100 Black, 42 | F52: =C50 -> 617342.36 | R52: Adriana Gonzalez | S52: 59490.702
B53: Sport-100 Helmet, Red | C53: 500346.22 | E53: =B51 -> Mountain-400-W Silver, 38 | F53: =C51 -> 564434.52 | R53: Latoya Goel | S53: 59483.488 | AA53: Age Group | AB53: =INDEX(AD25:AD29,MATCH(AB49,AE25:AE29,0)) -> 50 plus
B54: Mountain-400-W Silver, 42 | C54: 493792.78 | E54: =B52 -> Mountain-100 Silver, 48 | F54: =C52 -> 523718.13 | R54: Franklin Xu | S54: 59172.552
B55: Touring-2000 Blue, 50 | C55: 484522.96 | E55: =B53 -> Sport-100 Helmet, Red | F55: =C53 -> 500346.22 | R55: Kenneth Kumar | S55: 58741.257 | AA55: Caption | AB55: ="The"&" "&AB53&" "&"Age-group contributed" -> The 50 plus Age-group contributed
B56: Mountain-400-W Silver, 46 | C56: 484350.57 | E56: =B54 -> Mountain-400-W Silver, 42 | F56: =C54 -> 493792.78 | R56: Jermaine Lopez | S56: 58638.896
B57: Sport-100 Helmet, Blue | C57: 483414.66 | E57: =B55 -> Touring-2000 Blue, 50 | F57: =C55 -> 484522.96 | R57: Michele Nath | S57: 58394.799
B58: Touring-2000 Blue, 46 | C58: 475788.67 | E58: =B56 -> Mountain-400-W Silver, 46 | F58: =C56 -> 484350.57 | R58: Julio Ortega | S58: 58064.69
B59: Sport-100 Helmet, Black | C59: 475638.85 | E59: =B57 -> Sport-100 Helmet, Blue | F59: =C57 -> 483414.66 | R59: Kyle Patterson | S59: 57927.592
B60: Mountain-400-W Silver, 40 | C60: 471760.95 | E60: =B58 -> Touring-2000 Blue, 46 | F60: =C58 -> 475788.67 | R60: Tina Mehta | S60: 57496.546 | AA60: Country | AB60: Total Profit | AC60: Highlights | AE60: Country | AF60: =AB60 -> Total Profit | AG60: X | AH60: Y
B61: Touring-2000 Blue, 54 | C61: 431657.55 | E61: =B59 -> Sport-100 Helmet, Black | F61: =C59 -> 475638.85 | R61: Jon Zhou | S61: 56196.411 | AA61: Australia | AB61: 38700142 | AC61: {=IFERROR(_xlfn.IFS(AB61=$AL$61,AB61,AB61=$AL$62,AB61)," ")} -> 38700142 | AE61: =AA61 -> Australia | AF61: =AB61 -> 38700142 | AG61: 9 | AH61: 2 | AJ61: =INDEX($AA$61:$AA$66,MATCH(AL61,AB61:AB66,0)) -> United States | AK61: 1 | AL61: =LARGE($AB$61:$AB$66,AK61) -> 40537131
B62: Touring-2000 Blue, 60 | C62: 413729.28 | E62: =B60 -> Mountain-400-W Silver, 40 | F62: =C60 -> 471760.95 | R62: Sarah Garcia | S62: 56084.113 | AA62: Canada | AB62: 8776905.9 | AC62: {=IFERROR(_xlfn.IFS(AB62=$AL$61,AB62,AB62=$AL$62,AB62)," ")} | AE62: =AA62 -> Canada | AF62: =AB62 -> 8776905.9 | AG62: 1.5 | AH62: 8.5 | AJ62: =INDEX($AA$61:$AA$66,MATCH(AL62,$AB$61:$AB$66,0)) -> Australia | AK62: 2 | AL62: =LARGE($AB$61:$AB$66,AK62) -> 38700142
B63: HL Mountain Tire | C63: 323654.52 | E63: =B61 -> Touring-2000 Blue, 54 | F63: =C61 -> 431657.55 | R63: Kari Alvarez | S63: 55024.921 | AA63: France | AB63: 11125666 | AC63: {=IFERROR(_xlfn.IFS(AB63=$AL$61,AB63,AB63=$AL$62,AB63)," ")} | AE63: =AA63 -> France | AF63: =AB63 -> 11125666 | AG63: 1.5 | AH63: 7
B64: Fender Set - Mountain | C64: 303383.22 | E64: =B62 -> Touring-2000 Blue, 60 | F64: =C62 -> 413729.28 | R64: Isabel Barnes | S64: 54657.929 | AA64: Germany | AB64: 12419220 | AC64: {=IFERROR(_xlfn.IFS(AB64=$AL$61,AB64,AB64=$AL$62,AB64)," ")} | AE64: =AA64 -> Germany | AF64: =AB64 -> 12419220 | AG64: 4 | AH64: 9.4
B65: Road-650 Black, 52 | C65: 293256.61 | E65: =B63 -> HL Mountain Tire | F65: =C63 -> 323654.52 | R65: Crystal Wang | S65: 54553.266 | AA65: United Kingdom | AB65: 14731512 | AC65: {=IFERROR(_xlfn.IFS(AB65=$AL$61,AB65,AB65=$AL$62,AB65)," ")} | AE65: =AA65 -> United Kingdom | AF65: =AB65 -> 14731512 | AG65: 5 | AH65: 8 | AL65: =SUM(AL61:AL62)/SUM(AB61:AB66) -> 0.62742031
B66: Road-650 Red, 58 | C66: 277311.95 | E66: =B64 -> Fender Set - Mountain | F66: =C64 -> 303383.22 | R66: Rachael Sai | S66: 54543.528 | AA66: United States | AB66: 40537131 | AC66: {=IFERROR(_xlfn.IFS(AB66=$AL$61,AB66,AB66=$AL$62,AB66)," ")} -> 40537131 | AE66: =AA66 -> United States | AF66: =AB66 -> 40537131 | AG66: 4 | AH66: 8
B67: Hydration Pack - 70 oz. | C67: 268332.74 | E67: =B65 -> Road-650 Black, 52 | F67: =C65 -> 293256.61 | R67: Jessie Ramos | S67: 54497.35
B68: All-Purpose Bike Stand | C68: 266651.59 | E68: =B66 -> Road-650 Red, 58 | F68: =C66 -> 277311.95 | R68: Ricky Navarro | S68: 54341.696 | AJ68: Caption
B69: Road-650 Red, 48 | C69: 261925.88 | E69: =B67 -> Hydration Pack - 70 oz. | F69: =C67 -> 268332.74 | R69: Edgar Mehta | S69: 54299.859 | AJ69: =$AJ$61&" & "&$AJ$62&" "&"Contributed" -> United States & Australia Contributed
B70: Hitch Rack - 4-Bike | C70: 260516.16 | E70: =B68 -> All-Purpose Bike Stand | F70: =C68 -> 266651.59 | R70: Candace Raman | S70: 53969.05
B71: Road-650 Black, 58 | C71: 241554.65 | E71: =B69 -> Road-650 Red, 48 | F71: =C69 -> 261925.88 | R71: José Saraiva | S71: 53844.866
B72: Road-650 Black, 60 | C72: 230757.46 | E72: =B70 -> Hitch Rack - 4-Bike | F72: =C70 -> 260516.16 | R72: Jon Gao | S72: 53675.728
B73: Road-650 Red, 62 | C73: 227842.62 | E73: =B71 -> Road-650 Black, 58 | F73: =C71 -> 241554.65 | R73: Erika Rubio | S73: 53469.666
B74: ML Mountain Tire | C74: 226805.07 | E74: =B72 -> Road-650 Black, 60 | F74: =C72 -> 230757.46 | R74: Janet Ortega | S74: 53377.863
B75: Road-650 Black, 48 | C75: 212239.58 | E75: =B73 -> Road-650 Red, 62 | F75: =C73 -> 227842.62 | R75: Victor Carlson | S75: 53252.181
B76: Road-650 Red, 44 | C76: 204756.85 | E76: =B74 -> ML Mountain Tire | F76: =C74 -> 226805.07 | R76: Kaitlyn Henderson | S76: 52778.843
B77: Road-650 Black, 44 | C77: 196061.31 | E77: =B75 -> Road-650 Black, 48 | F77: =C75 -> 212239.58 | R77: Randall Dominguez | S77: 52445.403
B78: Road-650 Red, 52 | C78: 195172.46 | E78: =B76 -> Road-650 Red, 44 | F78: =C76 -> 204756.85 | R78: Melissa Patterson | S78: 51694.232
B79: HL Road Tire | C79: 186933.62 | E79: =B77 -> Road-650 Black, 44 | F79: =C77 -> 196061.31 | R79: Lacey He | S79: 51616.525
B80: Touring-3000 Blue, 62 | C80: 186801.96 | E80: =B78 -> Road-650 Red, 52 | F80: =C78 -> 195172.46 | R80: Colin Nath | S80: 51529.292
B81: Road-650 Black, 62 | C81: 186552.58 | E81: =B79 -> HL Road Tire | F81: =C79 -> 186933.62 | R81: Maria Hernandez | S81: 51180.516
... B135: Mountain Bike Socks, L | C135: 0 | E135: =B133 -> Racing Socks, L | F135: =C133 -> 15954.529 | R135: Johnny Shan | S135: 46963.388
B136: Thin-Jam Lock Nut 14 | C136: 0 | R136: Audrey Blanco | S136: 46816.083
B137: HL Touring Frame - Blue, 46 | C137: 0 | R137: Elizabeth Alexander | S137: 46782.43
B138: HL Road Frame - Black, 52 | C138: 0 | R138: Marco Lopez | S138: 46736.126
B139: HL Touring Frame - Blue, 50 | C139: 0 | R139: Ethan Bryant | S139: 46593.296
B140: HL Road Front Wheel | C140: 0 | R140: Alvin Hu | S140: 46476.755
B141: HL Touring Frame - Blue, 54 | C141: 0 | R141: Melinda Navarro | S141: 46455.32
B142: ML Road Frame - Red, 60 | C142: 0 | R142: Ross Sanz | S142: 46177.237
B143: HL Touring Frame - Blue, 60 | C143: 0 | R143: Tina Smith | S143: 46170.402
B144: External Lock Washer 1 | C144: 0 | R144: Gregory Becker | S144: 46147.466
B145: HL Touring Frame - Yellow, 46 | C145: 0 | R145: Dorothy Robinson | S145: 46002.306
B146: HL Road Frame - Red, 52 | C146: 0 | R146: Chad Kumar | S146: 45872.125
B147: HL Touring Frame - Yellow, 50 | C147: 0 | R147: Cindy Lewis | S147: 45815.342
... B507: Lock Washer 9 | C507: 0 | R507: Evelyn Gonzalez | S507: 35467.803
R508: Damien Chander | S508: 35455.322
R509: Mayra Mehta | S509: 35446.263
R510: Christian Jackson | S510: 35432.046
R511: Mary Perez | S511: 35430.307
R512: Damien Liu | S512: 35413.177
R513: Kate Raji | S513: 35412.385
...

Sheet Time Series Dashboard

Sheet Details Dashboard
